{
  "baseline_name": "isaac_v3_tall_upright_humanoid_direct",
  "task": "Isaac-Humanoid-Direct-v0",
  "reward_version": "isaac_v3_tall_upright",
  "loss_version": "isaac_rsl_rl_ppo_default",
  "checkpoint": "/workspace/IsaacLab/logs/rsl_rl/humanoid_direct/2026-05-09_13-55-22_tall_upright_v3/model_1525.pt",
  "tracking_script": "/workspace/IsaacLab/logs/rsl_rl/_humanoid_tracking_play.py",
  "source_video": "/workspace/IsaacLab/logs/rsl_rl/humanoid_direct/2026-05-09_13-55-22_tall_upright_v3/videos/play/rl-video-step-0.mp4",
  "copied_video": "outputs/videos/isaac_v3_policy_tracked.mp4",
  "num_envs": 1,
  "video_length": 180,
  "camera": {
    "distance": 5.0,
    "lateral": -2.0,
    "height": 2.2,
    "lookahead": 1.0,
    "look_height": 0.8
  },
  "elapsed_seconds": 24.2978572845459,
  "command": [
    "/workspace/IsaacLab/isaaclab.sh",
    "-p",
    "/workspace/IsaacLab/logs/rsl_rl/_humanoid_tracking_play.py",
    "--task",
    "Isaac-Humanoid-Direct-v0",
    "--num_envs",
    "1",
    "--checkpoint",
    "/workspace/IsaacLab/logs/rsl_rl/humanoid_direct/2026-05-09_13-55-22_tall_upright_v3/model_1525.pt",
    "--device",
    "cuda:0",
    "--video",
    "--video_length",
    "180",
    "--camera_tracking",
    "--camera_distance",
    "5.0",
    "--camera_lateral",
    "-2.0",
    "--camera_height",
    "2.2",
    "--camera_lookahead",
    "1.0",
    "--camera_look_height",
    "0.8",
    "--headless",
    "env.heading_weight=1.0",
    "env.up_weight=0.75",
    "env.energy_cost_scale=0.08",
    "env.actions_cost_scale=0.02",
    "env.alive_reward_scale=1.2",
    "env.death_cost=-4.0",
    "env.termination_height=1.0"
  ]
}